[{"name": "3104154", "index": 0}, {"name": "3107391", "index": 1}, {"name": "3107235", "index": 2}, {"name": "3107442", "index": 3}, {"name": "3106688", "index": 4}, {"name": "3107448", "index": 5}, {"name": "3102500", "index": 6}, {"name": "3103692", "index": 7}, {"name": "3107462", "index": 8}, {"name": "3102219", "index": 9}, {"name": "3107472", "index": 10}, {"name": "3107340", "index": 11}, {"name": "3107524", "index": 12}, {"name": "3104654", "index": 13}, {"name": "3102231", "index": 14}, {"name": "3103677", "index": 15}, {"name": "3102259", "index": 16}, {"name": "3104088", "index": 17}, {"name": "3102521", "index": 18}, {"name": "3102413", "index": 19}, {"name": "3104483", "index": 20}, {"name": "3102434", "index": 21}, {"name": "3103957", "index": 22}, {"name": "3103182", "index": 23}, {"name": "3102579", "index": 24}, {"name": "3102591", "index": 25}, {"name": "3104761", "index": 26}, {"name": "3102592", "index": 27}, {"name": "3104762", "index": 28}, {"name": "3102593", "index": 29}, {"name": "3103108", "index": 30}, {"name": "3102601", "index": 31}, {"name": "3103513", "index": 32}, {"name": "3103777", "index": 33}, {"name": "3103354", "index": 34}, {"name": "3102684", "index": 35}, {"name": "3102973", "index": 36}, {"name": "3104899", "index": 37}, {"name": "3104937", "index": 38}, {"name": "3105012", "index": 39}, {"name": "3103081", "index": 40}, {"name": "3105013", "index": 41}, {"name": "3105036", "index": 42}, {"name": "3103109", "index": 43}, {"name": "3105037", "index": 44}, {"name": "3105038", "index": 45}, {"name": "3103110", "index": 46}, {"name": "3105039", "index": 47}, {"name": "3105072", "index": 48}, {"name": "3105126", "index": 49}, {"name": "3105168", "index": 50}, {"name": "3105174", "index": 51}, {"name": "3105347", "index": 52}, {"name": "3103344", "index": 53}, {"name": "3105348", "index": 54}, {"name": "3103345", "index": 55}, {"name": "3105349", "index": 56}, {"name": "3105366", "index": 57}, {"name": "3105367", "index": 58}, {"name": "3103353", "index": 59}, {"name": "3105368", "index": 60}, {"name": "3105369", "index": 61}, {"name": "3105370", "index": 62}, {"name": "3105371", "index": 63}, {"name": "3105655", "index": 64}, {"name": "3105659", "index": 65}, {"name": "3103618", "index": 66}, {"name": "3105782", "index": 67}, {"name": "3104477", "index": 68}, {"name": "3105801", "index": 69}, {"name": "3103850", "index": 70}, {"name": "3105826", "index": 71}, {"name": "3105838", "index": 72}, {"name": "3103791", "index": 73}, {"name": "3103830", "index": 74}, {"name": "3104004", "index": 75}, {"name": "3105907", "index": 76}, {"name": "3105940", "index": 77}, {"name": "3105947", "index": 78}, {"name": "3106053", "index": 79}, {"name": "3106067", "index": 80}, {"name": "3106121", "index": 81}, {"name": "3106122", "index": 82}, {"name": "3106129", "index": 83}, {"name": "3106132", "index": 84}, {"name": "3106205", "index": 85}, {"name": "3106217", "index": 86}, {"name": "3104078", "index": 87}, {"name": "3106223", "index": 88}, {"name": "3106229", "index": 89}, {"name": "3106260", "index": 90}, {"name": "3106261", "index": 91}, {"name": "3104259", "index": 92}, {"name": "3106310", "index": 93}, {"name": "3104178", "index": 94}, {"name": "3106349", "index": 95}, {"name": "3106382", "index": 96}, {"name": "3106461", "index": 97}, {"name": "3106486", "index": 98}, {"name": "3106518", "index": 99}, {"name": "3106527", "index": 100}, {"name": "3104296", "index": 101}, {"name": "3106535", "index": 102}, {"name": "3106541", "index": 103}, {"name": "3106640", "index": 104}, {"name": "3106644", "index": 105}, {"name": "3106659", "index": 106}, {"name": "3106702", "index": 107}, {"name": "3106703", "index": 108}, {"name": "3106753", "index": 109}, {"name": "3106779", "index": 110}, {"name": "3106831", "index": 111}, {"name": "3106867", "index": 112}, {"name": "3104548", "index": 113}, {"name": "3104594", "index": 114}, {"name": "3106607", "index": 115}, {"name": "3104597", "index": 116}, {"name": "3106926", "index": 117}, {"name": "3104634", "index": 118}, {"name": "3106971", "index": 119}, {"name": "3106990", "index": 120}, {"name": "3107008", "index": 121}, {"name": "3104653", "index": 122}, {"name": "3107009", "index": 123}, {"name": "3107010", "index": 124}, {"name": "3104661", "index": 125}, {"name": "3107586", "index": 126}, {"name": "3108028", "index": 127}, {"name": "3108029", "index": 128}, {"name": "3108033", "index": 129}, {"name": "3108061", "index": 130}, {"name": "3108062", "index": 131}, {"name": "3108063", "index": 132}, {"name": "3108064", "index": 133}, {"name": "3108065", "index": 134}, {"name": "3108074", "index": 135}, {"name": "3108075", "index": 136}, {"name": "3108076", "index": 137}, {"name": "3108077", "index": 138}, {"name": "3108078", "index": 139}, {"name": "3108079", "index": 140}, {"name": "3108086", "index": 141}, {"name": "3108087", "index": 142}, {"name": "3108088", "index": 143}, {"name": "3108089", "index": 144}, {"name": "3108090", "index": 145}, {"name": "3108136", "index": 146}, {"name": "3108140", "index": 147}, {"name": "3108143", "index": 148}, {"name": "3108145", "index": 149}, {"name": "3108160", "index": 150}, {"name": "3108162", "index": 151}, {"name": "3108208", "index": 152}, {"name": "3108209", "index": 153}, {"name": "3108210", "index": 154}, {"name": "3108215", "index": 155}, {"name": "3108220", "index": 156}, {"name": "3108221", "index": 157}, {"name": "3108224", "index": 158}, {"name": "3108231", "index": 159}, {"name": "3108242", "index": 160}, {"name": "3108256", "index": 161}, {"name": "3108284", "index": 162}, {"name": "3108392", "index": 163}, {"name": "3108424", "index": 164}, {"name": "3108425", "index": 165}, {"name": "3108434", "index": 166}, {"name": "3108447", "index": 167}, {"name": "3108450", "index": 168}, {"name": "3108452", "index": 169}, {"name": "3108453", "index": 170}, {"name": "3108461", "index": 171}, {"name": "3108468", "index": 172}, {"name": "3108469", "index": 173}, {"name": "3108471", "index": 174}, {"name": "3108508", "index": 175}, {"name": "3108534", "index": 176}, {"name": "3108547", "index": 177}, {"name": "3108561", "index": 178}, {"name": "3108563", "index": 179}, {"name": "3108617", "index": 180}, {"name": "3108636", "index": 181}, {"name": "3108665", "index": 182}, {"name": "3108671", "index": 183}]