[{"name": "1p_code0", "c_nf_per_km": 0, "c0_nf_per_km": 0, "r_ohm_per_km": 1.247, "r0_ohm_per_km": 1.247, "x_ohm_per_km": 0.2494, "x0_ohm_per_km": 0.2494, "max_i_ka": 5, "std_type": "line"}, {"name": "1p_code3", "c_nf_per_km": 0, "c0_nf_per_km": 0, "r_ohm_per_km": 0.7839, "r0_ohm_per_km": 0.7839, "x_ohm_per_km": 0.0915, "x0_ohm_per_km": 0.0915, "max_i_ka": 5, "std_type": "line"}, {"name": "1p_code5", "c_nf_per_km": 0, "c0_nf_per_km": 0, "r_ohm_per_km": 1.29, "r0_ohm_per_km": 1.29, "x_ohm_per_km": 0.258, "x0_ohm_per_km": 0.258, "max_i_ka": 5, "std_type": "line"}, {"name": "1p_oh_code14", "c_nf_per_km": 0, "c0_nf_per_km": 0, "r_ohm_per_km": 1.2306, "r0_ohm_per_km": 1.2306, "x_ohm_per_km": 0.413, "x0_ohm_per_km": 0.413, "max_i_ka": 5, "std_type": "line"}, {"name": "2p_code13", "c_nf_per_km": 0, "c0_nf_per_km": 0, "r_ohm_per_km": 0.32, "r0_ohm_per_km": 0.32, "x_ohm_per_km": 0.063, "x0_ohm_per_km": 0.063, "max_i_ka": 5, "std_type": "line"}, {"name": "2p_code7", "c_nf_per_km": 0, "c0_nf_per_km": 0, "r_ohm_per_km": 1.247, "r0_ohm_per_km": 1.247, "x_ohm_per_km": 0.2494, "x0_ohm_per_km": 0.2494, "max_i_ka": 5, "std_type": "line"}, {"name": "3p_code10", "c_nf_per_km": 0, "c0_nf_per_km": 0, "r_ohm_per_km": 0.078, "r0_ohm_per_km": 0.312, "x_ohm_per_km": 0.061, "x0_ohm_per_km": 0.244, "max_i_ka": 5, "std_type": "line"}, {"name": "3p_code11", "c_nf_per_km": 0, "c0_nf_per_km": 0, "r_ohm_per_km": 0.7839, "r0_ohm_per_km": 3.1356, "x_ohm_per_km": 0.0915, "x0_ohm_per_km": 0.366, "max_i_ka": 5, "std_type": "line"}, {"name": "3p_code12", "c_nf_per_km": 0, "c0_nf_per_km": 0, "r_ohm_per_km": 1.247, "r0_ohm_per_km": 4.988, "x_ohm_per_km": 0.2494, "x0_ohm_per_km": 0.9976, "max_i_ka": 5, "std_type": "line"}, {"name": "3p_code15", "c_nf_per_km": 0, "c0_nf_per_km": 0, "r_ohm_per_km": 1.29, "r0_ohm_per_km": 5.16, "x_ohm_per_km": 0.258, "x0_ohm_per_km": 1.032, "max_i_ka": 5, "std_type": "line"}, {"name": "3p_code2", "c_nf_per_km": 0, "c0_nf_per_km": 0, "r_ohm_per_km": 0.32, "r0_ohm_per_km": 1.28, "x_ohm_per_km": 0.063, "x0_ohm_per_km": 0.252, "max_i_ka": 5, "std_type": "line"}, {"name": "3p_code6", "c_nf_per_km": 0, "c0_nf_per_km": 0, "r_ohm_per_km": 0.164, "r0_ohm_per_km": 0.656, "x_ohm_per_km": 0.062, "x0_ohm_per_km": 0.248, "max_i_ka": 5, "std_type": "line"}, {"name": "3p_code9", "c_nf_per_km": 0, "c0_nf_per_km": 0, "r_ohm_per_km": 0.1, "r0_ohm_per_km": 0.4, "x_ohm_per_km": 0.061, "x0_ohm_per_km": 0.244, "max_i_ka": 5, "std_type": "line"}, {"name": "3p_oh_code1", "c_nf_per_km": 0, "c0_nf_per_km": 0, "r_ohm_per_km": 0.3751, "r0_ohm_per_km": 1.5004, "x_ohm_per_km": 0.3601, "x0_ohm_per_km": 1.4404, "max_i_ka": 5, "std_type": "line"}, {"name": "3p_oh_code4", "c_nf_per_km": 0, "c0_nf_per_km": 0, "r_ohm_per_km": 0.5875, "r0_ohm_per_km": 2.35, "x_ohm_per_km": 0.3745, "x0_ohm_per_km": 1.498, "max_i_ka": 5, "std_type": "line"}, {"name": "3p_oh_code8", "c_nf_per_km": 0, "c0_nf_per_km": 0, "r_ohm_per_km": 0.2614, "r0_ohm_per_km": 1.0456, "x_ohm_per_km": 0.3489, "x0_ohm_per_km": 1.3956, "max_i_ka": 5, "std_type": "line"}]